wog/CurrencyRouletteGame.py
wog/Game.py
wog/GuessGame.py
wog/Live.py
wog/MainGame.py
wog/MainScores.py
wog/MemoryGame.py
wog/Score.py
wog/Scores.txt
wog/Utils.py
wog/__init__.py
wog/__main__.py
wog/error_html.html
wog/scores_html.html
wog/tests/e2e.py
wog_tomer9000-2.5.dist-info/LICENSE
wog_tomer9000-2.5.dist-info/METADATA
wog_tomer9000-2.5.dist-info/WHEEL
wog_tomer9000-2.5.dist-info/top_level.txt
wog_tomer9000-2.5.dist-info/RECORD
