Metadata-Version: 2.1
Name: wog-tomer9000
Version: 2.5
Summary: Package for DevOps course
Home-page: https://github.com/Tomer9000/WOG
Author: Tomer_Tzur
Author-email: tomer9000@gmail.com
License: UNKNOWN
Platform: UNKNOWN
Classifier: Programming Language :: Python :: 3
Classifier: License :: OSI Approved :: MIT License
Classifier: Operating System :: OS Independent
Requires-Python: >=3.4
Requires-Dist: inputimeout
Requires-Dist: requests
Requires-Dist: flask
Requires-Dist: selenium
